packageLab2/_init_.py
packageLab2/function.py
packageLab2Sets-0.1.dist-info/METADATA
packageLab2Sets-0.1.dist-info/WHEEL
packageLab2Sets-0.1.dist-info/top_level.txt
packageLab2Sets-0.1.dist-info/RECORD
