Metadata-Version: 2.1
Name: packageLab2Sets
Version: 0.1
Summary: Conflict package for Lab2
Home-page: UNKNOWN
Author: UNKNOWN
Author-email: UNKNOWN
License: UNKNOWN
Platform: UNKNOWN
Requires-Dist: pandas (<1.0)
